[
  //////// Nerf Spider speed ////////
  {
    "difficulty": "hard",
    "gamestage": "nerf_enemies",
    "mob": ["minecraft:spider", "minecraft:cave_spider"],
    "spawner": false,
    "incontrol": false,

    "speedmultiply": 0.7,

    "continue": true
  },
  //////// Buff Enemies ////////
  {
    "difficulty": "hard",
    "dimension": "minecraft:overworld",
    "gamestage": "enter_the_end",
    "hostile": true,

    "healthmultiply": 1.3,
    "damagemultiply": 1.4,
    "speedmultiply": 1.1,

    "continue": true
  },
  //////// Harder spawner ////////
  {
    "difficulty": "hard",
    "hostile": true,
    "spawner": true,

    "result": "allow"
  },
  //////// Nerf Enemies and CHILL Exclusion ////////
  {
    "difficulty": "hard",
    "dimension": "minecraft:overworld",
    "gamestage": "nerf_enemies",
    "mod": ["irons_spellbooks", "witherstormmod", "bosses_of_mass_destruction"],
    "hostile": true,
    "spawner": false,
    "incontrol": false,

    "result": "default"
  },
  {
    "difficulty": "hard",
    "dimension": "minecraft:overworld",
    "gamestage": "nerf_enemies",
    "mob": ["minecraft:wither"],
    "hostile": true,
    "spawner": false,
    "incontrol": false,

    "result": "default"
  },
  //////// Nerf Enemies ////////
  {
    "difficulty": "hard",
    "dimension": "minecraft:overworld",
    "gamestage": "nerf_enemies",
    "hostile": true,
    "spawner": false,
    "incontrol": false,

    "healthmultiply": 0.7,

    "continue": true
  },
  /////// Days for CHILL ////////
  {
    "dimension": "minecraft:overworld",
    "gamestage": "nerf_enemies",
    "mob": ["minecraft:guardian", "minecraft:elder_guardian", "warden_and_sculk:warden"],
    "maxdaycount": 11,
    "spawner": false,

    "result": "default"
  },
  {
    "dimension": "minecraft:overworld",
    "gamestage": "nerf_enemies",
    "hostile": true,
    "maxdaycount": 11,
    "spawner": false,

    "result": "deny"
  },
  //////// Only Night Spawn ////////
  {
    "difficulty": "hard",
    "dimension": "minecraft:overworld",
    "gamestage": "nerf_enemies",
    "hostile": true,
    "spawner": false,
    "time": "outsideRange(13000,23000)",

    "result": "deny"
  },
  //////// Reduce Spawn ////////
  {
    "difficulty": "hard",
    "dimension": "minecraft:overworld",
    "gamestage": "nerf_enemies",
    "mob": "minecraft:skeleton",
    "spawner": false,
    "incontrol": false,
    "mincount": {
      "amount": 3,
      "mob": "minecraft:skeleton",
      "perplayer": true
    },

    "result": "deny"
  },
  {
    "difficulty": "hard",
    "dimension": "minecraft:overworld",
    "gamestage": "nerf_enemies",
    "mob": "minecraft:drowned",
    "spawner": false,
    "incontrol": false,
    "mincount": {
      "amount": 6,
      "mob": "minecraft:drowned",
      "perplayer": true
    },

    "result": "deny"
  },
  {
    "difficulty": "hard",
    "dimension": "minecraft:overworld",
    "gamestage": "nerf_enemies",
    "mob": "minecraft:creeper",
    "spawner": false,
    "incontrol": false,
    "mincount": {
      "amount": 3,
      "mob": "minecraft:creeper",
      "perplayer": true
    },

    "result": "deny"
  },
  {
    "difficulty": "hard",
    "dimension": "minecraft:overworld",
    "gamestage": "nerf_enemies",
    "mob": ["minecraft:spider", "minecraft:cave_spider"],
    "spawner": false,
    "incontrol": false,
    "mincount": {
      "amount": 3,
      "mob": ["minecraft:spider", "minecraft:cave_spider"],
      "perplayer": true
    },

    "result": "deny"
  },
  {
    "difficulty": "hard",
    "dimension": "minecraft:overworld",
    "gamestage": "nerf_enemies",
    "hostile": true,
    "spawner": false,
    "incontrol": false,
    "mincount": {
      "amount": 50,
      "hostile": true,
      "perplayer": true
    },

    "result": "deny"
  },
  {
    "difficulty": "hard",
    "dimension": "minecraft:overworld",
    "gamestage": "nerf_enemies",
    "hostile": true,
    "spawner": false,
    "incontrol": false,
    "mincount": {
      "amount": 2,
      "hostile": true,
      "perchunk": true
    },

    "result": "deny"
  },
  //////// Enderman with End stone ////////
  {
    "difficulty": "hard",
    "dimension": "minecraft:overworld",
    "mob": "minecraft:enderman",
    "random": 0.1,

    "helditem": "minecraft:end_stone",

    "continue": true
  },
  //////// Nether Visited ////////
  {
    "difficulty": "hard",
    "dimension": "minecraft:overworld",
    "gamestage": "enter_the_nether",
    "mob": "minecraft:spider",
    "seesky": false,
    "random": 0.1,

    "healthmultiply": 0.25,
    "speedmultiply": 2.0,
    "potion": "minecraft:invisibility,9999,1"
  },
  {
    "difficulty": "hard",
    "dimension": "minecraft:overworld",
    "gamestage": "enter_the_nether",
    "mob": "minecraft:zombie",
    "baby": false,
    "seesky": false,
    "random": 0.1,

    "customname": "Воин",
    "healthmultiply": 1.5,
    "speedmultiply": 0.90,
    "helditem": "minecraft:iron_axe",
    "armorboots": "minecraft:iron_boots",
    "armorhelmet": "minecraft:iron_helmet",
    "armorlegs": "minecraft:iron_leggings",
    "armorchest": "minecraft:iron_chestplate",
    "nbt": {"IsBaby":false}
  },
  {
    "gamestage": "enter_the_nether",
    "difficulty": "hard",
    "dimension": "minecraft:overworld",
    "mob": "minecraft:zombie",
    "baby": false,
    "seesky": true,
    "random": 0.05,

    "customname": "Берсерк",
    "speedmultiply": 1.5,
    "damagemultiply": 1.5,
    "helditem": "minecraft:golden_axe",
    "armorboots": "minecraft:golden_boots",
    "armorhelmet": "minecraft:golden_helmet",
    "armorlegs": "minecraft:golden_leggings",
    "armorchest": "minecraft:golden_chestplate",
    "nbt": {"IsBaby":false}
  },
  {
    "gamestage": "enter_the_nether",
    "difficulty": "hard",
    "dimension": "minecraft:overworld",
    "mob": "minecraft:zombie",
    "baby": false,
    "random": 0.01,

    "customname": "Джаггернаут",
    "speedmultiply": 0.80,
    "damagemultiply": 2.0,
    "healthmultiply": 3.0,
    "helditem": {
      "item": "minecraft:diamond_axe",
      "nbt": {"Enchantments":[{"id": "minecraft:knockback","lvl": 5}]}
    },
    "armorboots": "minecraft:diamond_boots",
    "armorhelmet": {
      "item": "minecraft:diamond_helmet",
      "nbt": {"Enchantments":[{"id": "minecraft:unbreaking","lvl": 3}]}
    },
    "armorlegs": "minecraft:diamond_leggings",
    "armorchest": "minecraft:diamond_chestplate",
    "nbt": {"IsBaby":false}
  },
  {
    "gamestage": "enter_the_nether",
    "difficulty": "hard",
    "dimension": "minecraft:overworld",
    "mob": "minecraft:skeleton",
    "seesky": false,
    "random": 0.05,

    "healthmultiply": 0.25,
    "speedmultiply": 2.0,
    "potion": "minecraft:invisibility,9999,1"
  },
  //////// End Visited ////////
  {
    "gamestage": "enter_the_end",
    "difficulty": "hard",
    "dimension": "minecraft:overworld",
    "mob": "minecraft:enderman",
    "random": 0.3,

    "customname": "Контуженный",
    "angry": true,
    "speedmultiply": 0.75,
    "helditem": "minecraft:end_stone"
  },
  {
    "gamestage": "enter_the_end",
    "difficulty": "hard",
    "dimension": "minecraft:overworld",
    "mob": "minecraft:skeleton",
    "onjoin": true,
    "seesky": true,

    "random": 0.1,

    "customname": "Вышибала",
    "healthmultiply": 0.5,
    "speedmultiply": 1.75,
    "damagemultiply": 1.5,
    "helditem": {
        "item": "minecraft:bow",
        "nbt": {"Enchantments":[{"id": "minecraft:punch","lvl": 5}]}
    },
    "potion": "minecraft:fire_resistance,9999,1",
    "armorboots": "minecraft:chainmail_boots",
    "armorhelmet": "minecraft:chainmail_helmet",
    "armorlegs": "minecraft:chainmail_leggings",
    "armorchest": {
        "item": "minecraft:chainmail_chestplate",
        "nbt": {"Enchantments":[{"id": "minecraft:projectile_protection","lvl": 5}]}
    }
  },
  //////// END /////////
  {
    "difficulty": "hard",
    "dimension": "minecraft:the_end",
    "mob": "minecraft:enderman",
    "random": 0.1,

    "angry": true,
    "healthmultiply": 0.75,
    "speedmultiply": 0.80
  },
  {
    "difficulty": "hard",
    "dimension": "minecraft:the_end",
    "mob": "minecraft:ender_dragon",

    "speedmultiply": 1.5
  },
  {
    "difficulty": "hard",
    "dimension": "minecraft:the_end",
    "mob": "wrd:ender_miner",

    "speedmultiply": 0.75,

    "continue": true
  },
  {
    "difficulty": "hard",
    "dimension": "minecraft:the_end",
    "mob": "wrd:ender_miner",
    "mincount": 15,

    "result": "deny"
  },
  //////// HELL /////////
  {
    "difficulty": "hard",
    "dimension": "minecraft:the_nether",
    "onjoin": true,
    "mob": "minecraft:zombie",
    "random": 0.2,

    "customname": "Копатель",
    "healthmultiply": 1.3,
    "damagemultiply": 1.1,
    "speedmultiply": 1.1,
    "helditem": "minecraft:golden_shovel",
    "potion": "minecraft:fire_resistance,9999,1"
  },
  {
    "difficulty": "hard",
    "dimension": "minecraft:the_nether",
    "mob": "minecraft:zombie",

    "customname": "Грешник",
    "healthmultiply": 1.2,
    "damagemultiply": 1.1,
    "speedmultiply": 1.3,
    "potion": "minecraft:fire_resistance,9999,1"
  },
  {
    "difficulty": "hard",
    "dimension": "minecraft:the_nether",
    "mob": "minecraft:skeleton",
    "onjoin": true,
    "random": 0.5,

    "customname": "Вышибала",
    "healthmultiply": 0.5,
    "speedmultiply": 2.0,
    "damagemultiply": 1.5,
    "helditem": {
      "item": "minecraft:bow",
      "nbt": {"Enchantments":[{"id": "minecraft:punch", "lvl": 5}]}
    },
    "potion": "minecraft:fire_resistance,9999,1",
    "armorhelmet": "minecraft:chainmail_helmet",
    "armorboots": "minecraft:chainmail_boots"
  },
  {
    "difficulty": "hard",
    "dimension": "minecraft:the_nether",
    "mob": "minecraft:skeleton",
    "onjoin": true,

    "customname": "Поджигатель",
    "healthmultiply": 0.5,
    "speedmultiply": 1.5,
    "helditem": {
      "item": "minecraft:bow",
      "nbt": {"Enchantments":[{"id": "minecraft:flame","lvl": 1}]}
    },
    "potion": "minecraft:fire_resistance,9999,1",
    "armorhelmet": "minecraft:golden_helmet",
    "armorboots": "minecraft:golden_boots"
  }
]